a2y_sql/__init__.py
a2y_sql-0.8.0.dist-info/METADATA
a2y_sql-0.8.0.dist-info/WHEEL
a2y_sql-0.8.0.dist-info/top_level.txt
a2y_sql-0.8.0.dist-info/RECORD
