Metadata-Version: 2.1
Name: a2y-sql
Version: 0.8.0
Summary: A module that implements some SQL handy tools.
Home-page: http://www.sorobust.com/a2y/sql.html
Author: Yu Han
Author-email: hanjunyu@163.com
License: Private
Platform: Windows
Platform: Linux
Classifier: Development Status :: 4 - Beta
Classifier: Intended Audience :: Developers
Classifier: License :: Free For Educational Use
Classifier: Programming Language :: Python :: 3.5
Classifier: Operating System :: Microsoft :: Windows :: Windows 10
Classifier: Operating System :: POSIX :: Linux
Requires-Dist: mysql-connector (>=2.2.6)
